pudly/__init__.py
pudly/exceptions.py
pudly/pudly.py
pudly-2.0.0.dist-info/LICENSE
pudly-2.0.0.dist-info/METADATA
pudly-2.0.0.dist-info/WHEEL
pudly-2.0.0.dist-info/top_level.txt
pudly-2.0.0.dist-info/RECORD
