Metadata-Version: 2.1
Name: pudly
Version: 2.0.0
Summary: Add your description here
Author-email: Kristof Kovacs <kristof.kovacs1996@gmail.com>
Project-URL: Homepage, https://github.com/8-bit-hunters/pudly
Project-URL: Documentation, https://8-bit-hunters.github.io/pudly/
Requires-Python: >=3.12
License-File: LICENSE
Requires-Dist: requests>=2.32.3
